fastelectrons/__init__.py
fastelectrons/_version.py
fastelectrons-0.0.2.dist-info/METADATA
fastelectrons-0.0.2.dist-info/WHEEL
fastelectrons-0.0.2.dist-info/licenses/LICENSE
fastelectrons-0.0.2.dist-info/RECORD
