Metadata-Version: 2.4
Name: fastelectrons
Version: 0.0.2
Summary: Electronic structure calculations for molecules and solids.
Project-URL: Homepage, https://github.com/leseixas/fastelectrons
Author-email: Leandro Seixas <leandro.fisica@gmail.com>
License: MIT License
License-File: LICENSE
Classifier: License :: OSI Approved :: MIT License
Classifier: Operating System :: OS Independent
Classifier: Programming Language :: Python :: 3
Classifier: Topic :: Scientific/Engineering :: Chemistry
Classifier: Topic :: Scientific/Engineering :: Physics
Requires-Python: >=3.9
Requires-Dist: ase
Requires-Dist: numpy
Requires-Dist: pandas
